infi.gitlab_copy_id-0.0.6-py2.7-nspkg.pth
infi/gitlab_copy_id/__init__.py
infi/gitlab_copy_id/__version__.py
infi.gitlab_copy_id-0.0.6.dist-info/DESCRIPTION.rst
infi.gitlab_copy_id-0.0.6.dist-info/METADATA
infi.gitlab_copy_id-0.0.6.dist-info/RECORD
infi.gitlab_copy_id-0.0.6.dist-info/WHEEL
infi.gitlab_copy_id-0.0.6.dist-info/entry_points.txt
infi.gitlab_copy_id-0.0.6.dist-info/metadata.json
infi.gitlab_copy_id-0.0.6.dist-info/namespace_packages.txt
infi.gitlab_copy_id-0.0.6.dist-info/top_level.txt
