Metadata-Version: 2.0
Name: infi.gitlab-copy-id
Version: 0.0.6
Summary: A script like ssh-copy-id, only that copies it to GitLab
Home-page: https://git.infinidat.com/host-opensource/infi.gitlab_copy_id
Author: Arnon Yaari
Author-email: arnony@infinidat.com
License: BSD
Platform: UNKNOWN
Classifier: Intended Audience :: Developers
Classifier: Intended Audience :: System Administrators
Classifier: License :: OSI Approved :: BSD License
Classifier: Operating System :: OS Independent
Classifier: Programming Language :: Python
Classifier: Topic :: Software Development :: Libraries :: Python Modules
Requires-Dist: dnspython
Requires-Dist: docopt
Requires-Dist: requests
Requires-Dist: setuptools
